README.rst
FlashPy/__init__.py
FlashPy/analysis.py
FlashPy/data.py
FlashPy/visualisation.py
FlashPy-0.0.2.dist-info/DESCRIPTION.rst
FlashPy-0.0.2.dist-info/METADATA
FlashPy-0.0.2.dist-info/RECORD
FlashPy-0.0.2.dist-info/WHEEL
FlashPy-0.0.2.dist-info/metadata.json
FlashPy-0.0.2.dist-info/top_level.txt
